{
  "a20b9144-6e78-4569-becb-c960642a57f3": {
    "event_category": "other",
    "sub_category": "general_market_news",
    "affected_tickers": [
      "SPY",
      "QQQ"
    ],
    "sector_impact": [
      "broad_market"
    ],
    "ticker_impact_weights": {
      "SPY": 0.5,
      "QQQ": 0.4
    }
  },
  "13f41470-d755-41b5-acc2-9b2338427de4": {
    "event_category": "earnings_data",
    "sub_category": "delivery_report",
    "affected_tickers": [
      "TSLA",
      "QQQ",
      "SPY"
    ],
    "sector_impact": [
      "automotive",
      "technology",
      "broad_market"
    ],
    "ticker_impact_weights": {
      "TSLA": 1.0,
      "QQQ": 0.4,
      "SPY": 0.3
    }
  },
  "cf197a02-7cd9-4a16-9581-760e9d83b54d": {
    "event_category": "corporate_action",
    "sub_category": "executive_change",
    "affected_tickers": [
      "DJT"
    ],
    "sector_impact": [
      "media",
      "technology"
    ],
    "ticker_impact_weights": {
      "DJT": 1.0
    }
  },
  "75db4570-c075-4d53-9edf-4a438e5b304e": {
    "event_category": "corporate_action",
    "sub_category": "bankruptcy_negotiation",
    "affected_tickers": [
      "SPY"
    ],
    "sector_impact": [
      "airlines",
      "transportation",
      "financials"
    ],
    "ticker_impact_weights": {
      "SPY": 0.2
    }
  },
  "35f6314d-0b7f-4c75-b95a-09af3964e09a": {
    "event_category": "other",
    "sub_category": "political_endorsement",
    "affected_tickers": [
      "TSLA",
      "DJT",
      "SPY"
    ],
    "sector_impact": [
      "automotive",
      "media",
      "broad_market"
    ],
    "ticker_impact_weights": {
      "TSLA": 0.5,
      "DJT": 0.5,
      "SPY": 0.2
    }
  },
  "d82de28e-3e0d-490e-865d-2f8fbcd3a3ac": {
    "event_category": "regulatory",
    "sub_category": "antitrust_lawsuit",
    "affected_tickers": [
      "AMZN",
      "QQQ",
      "SPY"
    ],
    "sector_impact": [
      "technology",
      "e-commerce"
    ],
    "ticker_impact_weights": {
      "AMZN": 1.0,
      "QQQ": 0.4,
      "SPY": 0.3
    }
  },
  "b6ab5c17-e78e-4dfe-a72a-c5705617fab1": {
    "event_category": "regulatory",
    "sub_category": "antitrust_ruling",
    "affected_tickers": [
      "GOOG",
      "AAPL",
      "QQQ",
      "SPY"
    ],
    "sector_impact": [
      "technology",
      "mobile_app_ecosystem"
    ],
    "ticker_impact_weights": {
      "GOOG": 1.0,
      "AAPL": 0.3,
      "QQQ": 0.4,
      "SPY": 0.3
    }
  },
  "86b786c1-96dd-4e18-9a7e-b265840b6bbc": {
    "event_category": "regulatory",
    "sub_category": "antitrust_ruling",
    "affected_tickers": [
      "GOOG",
      "AAPL",
      "QQQ",
      "SPY"
    ],
    "sector_impact": [
      "technology",
      "mobile_app_ecosystem"
    ],
    "ticker_impact_weights": {
      "GOOG": 1.0,
      "AAPL": 0.3,
      "QQQ": 0.4,
      "SPY": 0.3
    }
  },
  "bfcbcc38-0264-4a7c-84ae-375420ee7947": {
    "event_category": "regulatory",
    "sub_category": "antitrust_ruling",
    "affected_tickers": [
      "GOOG",
      "AAPL",
      "QQQ",
      "SPY"
    ],
    "sector_impact": [
      "technology",
      "mobile_app_ecosystem"
    ],
    "ticker_impact_weights": {
      "GOOG": 1.0,
      "AAPL": 0.3,
      "QQQ": 0.4,
      "SPY": 0.3
    }
  },
  "e98ca6e4-671c-4d56-8fa8-684eb9f37c0f": {
    "event_category": "regulatory",
    "sub_category": "antitrust_appeal",
    "affected_tickers": [
      "GOOG",
      "AAPL",
      "QQQ",
      "SPY"
    ],
    "sector_impact": [
      "technology",
      "mobile_app_ecosystem"
    ],
    "ticker_impact_weights": {
      "GOOG": 1.0,
      "AAPL": 0.3,
      "QQQ": 0.4,
      "SPY": 0.3
    }
  },
  "11b22633-dd21-4e9a-b6e2-e8f29987a313": {
    "event_category": "corporate_action",
    "sub_category": "company_statement",
    "affected_tickers": [],
    "sector_impact": [
      "technology",
      "gaming"
    ],
    "ticker_impact_weights": {}
  },
  "d403a697-e3c9-4a9a-b79f-e41464c544a0": {
    "event_category": "other",
    "sub_category": "political_endorsement_discussion",
    "affected_tickers": [
      "JPM",
      "SPY"
    ],
    "sector_impact": [
      "financials"
    ],
    "ticker_impact_weights": {
      "JPM": 0.5,
      "SPY": 0.2
    }
  },
  "a40b2f33-3219-4dc6-aedf-df335f49b9b9": {
    "event_category": "corporate_action",
    "sub_category": "company_statement",
    "affected_tickers": [],
    "sector_impact": [
      "technology",
      "gaming"
    ],
    "ticker_impact_weights": {}
  },
  "2d456c41-d794-4bc3-b735-92d5aa711112": {
    "event_category": "geopolitical_conflict",
    "sub_category": "platform_ban",
    "affected_tickers": [],
    "sector_impact": [
      "technology",
      "communication"
    ],
    "ticker_impact_weights": {}
  },
  "aba87467-390b-4f76-867c-56ddd4a2088f": {
    "event_category": "geopolitical_conflict",
    "sub_category": "military_action",
    "affected_tickers": [
      "GLD",
      "SPY",
      "BA",
      "QQQ"
    ],
    "sector_impact": [
      "defense",
      "energy",
      "broad_market"
    ],
    "ticker_impact_weights": {
      "GLD": 0.4,
      "SPY": 0.3,
      "BA": 0.3,
      "QQQ": 0.2
    }
  },
  "72b195bf-c41f-430f-98d8-cd0607d37372": {
    "event_category": "corporate_action",
    "sub_category": "credit_rating_warning",
    "affected_tickers": [
      "BA",
      "SPY"
    ],
    "sector_impact": [
      "aerospace",
      "industrials"
    ],
    "ticker_impact_weights": {
      "BA": 1.0,
      "SPY": 0.3
    }
  },
  "1b285d77-5571-4005-beb4-5f7aacaeb5a3": {
    "event_category": "regulatory",
    "sub_category": "platform_ban_lifted",
    "affected_tickers": [],
    "sector_impact": [
      "technology",
      "social_media"
    ],
    "ticker_impact_weights": {}
  },
  "cbd66d99-bc92-4405-8a1d-81bacb363b43": {
    "event_category": "regulatory",
    "sub_category": "antitrust_remedy",
    "affected_tickers": [
      "GOOG",
      "AAPL",
      "QQQ",
      "SPY"
    ],
    "sector_impact": [
      "technology",
      "internet"
    ],
    "ticker_impact_weights": {
      "GOOG": 1.0,
      "AAPL": 0.5,
      "QQQ": 0.4,
      "SPY": 0.4
    }
  },
  "0dadbb6b-3fc8-4965-b813-ac7986627e38": {
    "event_category": "regulatory",
    "sub_category": "antitrust_remedy",
    "affected_tickers": [
      "GOOG",
      "AAPL",
      "QQQ",
      "SPY"
    ],
    "sector_impact": [
      "technology",
      "internet"
    ],
    "ticker_impact_weights": {
      "GOOG": 1.0,
      "AAPL": 0.5,
      "QQQ": 0.4,
      "SPY": 0.4
    }
  },
  "061e5b24-874c-47a6-91e0-e167cbd76206": {
    "event_category": "corporate_action",
    "sub_category": "fleet_expansion",
    "affected_tickers": [
      "AMZN",
      "TSLA",
      "QQQ",
      "SPY"
    ],
    "sector_impact": [
      "e-commerce",
      "electric_vehicles",
      "technology"
    ],
    "ticker_impact_weights": {
      "AMZN": 0.8,
      "TSLA": 0.2,
      "QQQ": 0.2,
      "SPY": 0.2
    }
  },
  "da43ea9f-edf9-4644-964d-fa9ef08e6b65": {
    "event_category": "geopolitical_conflict",
    "sub_category": "tensions_statement",
    "affected_tickers": [
      "GLD",
      "SPY",
      "BA",
      "QQQ"
    ],
    "sector_impact": [
      "energy",
      "defense",
      "broad_market"
    ],
    "ticker_impact_weights": {
      "GLD": 0.4,
      "SPY": 0.3,
      "BA": 0.3,
      "QQQ": 0.2
    }
  },
  "f6e1f8a1-1f44-4342-808f-4352150597c1": {
    "event_category": "corporate_action",
    "sub_category": "trading_halt",
    "affected_tickers": [],
    "sector_impact": [
      "healthcare"
    ],
    "ticker_impact_weights": {}
  },
  "2861da60-48ab-4538-a55c-0d13cab58cc2": {
    "event_category": "corporate_action",
    "sub_category": "legal_settlement",
    "affected_tickers": [],
    "sector_impact": [
      "healthcare"
    ],
    "ticker_impact_weights": {}
  },
  "6ffe0c12-1cd6-49dd-986e-f1e8b71a0152": {
    "event_category": "other",
    "sub_category": "political_statement",
    "affected_tickers": [
      "DJT"
    ],
    "sector_impact": [
      "media",
      "broad_market"
    ],
    "ticker_impact_weights": {
      "DJT": 0.5
    }
  },
  "1475aaef-2e39-4019-b778-046b8cbc097d": {
    "event_category": "regulatory",
    "sub_category": "aml_enforcement",
    "affected_tickers": [
      "JPM",
      "SPY"
    ],
    "sector_impact": [
      "financials",
      "broad_market"
    ],
    "ticker_impact_weights": {
      "JPM": 0.3,
      "SPY": 0.1
    }
  },
  "c45f93e0-90a2-4cf0-9116-f4db7c5f4fb4": {
    "event_category": "regulatory",
    "sub_category": "aml_settlement",
    "affected_tickers": [
      "JPM",
      "SPY"
    ],
    "sector_impact": [
      "financials",
      "broad_market"
    ],
    "ticker_impact_weights": {
      "JPM": 0.3,
      "SPY": 0.1
    }
  },
  "10becb1c-125a-4d8e-a57a-43220dae0c38": {
    "event_category": "corporate_action",
    "sub_category": "production_update",
    "affected_tickers": [
      "TSLA"
    ],
    "sector_impact": [
      "technology"
    ],
    "ticker_impact_weights": {
      "TSLA": 1.0
    }
  },
  "00b7c7ef-221f-4cc6-8963-ccb3345fa819": {
    "event_category": "corporate_action",
    "sub_category": "product_demo_controversy",
    "affected_tickers": [
      "TSLA"
    ],
    "sector_impact": [
      "technology"
    ],
    "ticker_impact_weights": {
      "TSLA": 1.0
    }
  },
  "a5704462-b6a4-4040-abc2-9dc75935e7cd": {
    "event_category": "geopolitical_conflict",
    "sub_category": "military_strike_plan",
    "affected_tickers": [
      "BA",
      "GLD",
      "SPY"
    ],
    "sector_impact": [
      "defense_military",
      "energy_commodity",
      "broad_market"
    ],
    "ticker_impact_weights": {
      "BA": 0.5,
      "GLD": 0.4,
      "SPY": 0.3
    }
  },
  "2def0f75-528f-4699-9341-c9c151885d89": {
    "event_category": "other",
    "sub_category": "political_media_appearance",
    "affected_tickers": [
      "DJT"
    ],
    "sector_impact": [
      "media",
      "broad_market"
    ],
    "ticker_impact_weights": {
      "DJT": 0.4
    }
  },
  "1c7f73cf-d1d3-442e-abfe-9b3f844dc711": {
    "event_category": "fed_policy",
    "sub_category": "fed_speaker_crypto",
    "affected_tickers": [
      "IBIT",
      "MSTR",
      "COIN"
    ],
    "sector_impact": [
      "cryptocurrency",
      "technology"
    ],
    "ticker_impact_weights": {
      "IBIT": 0.9,
      "MSTR": 0.8,
      "COIN": 0.8
    }
  },
  "17ba98ea-b881-4f7e-9589-569bcaf3870e": {
    "event_category": "geopolitical_conflict",
    "sub_category": "iran_threats_us_officials",
    "affected_tickers": [
      "DJT",
      "GLD",
      "SPY"
    ],
    "sector_impact": [
      "defense_military",
      "broad_market"
    ],
    "ticker_impact_weights": {
      "DJT": 0.3,
      "GLD": 0.2,
      "SPY": 0.1
    }
  },
  "003d571e-1cad-488e-8034-dcdeaa7ad157": {
    "event_category": "geopolitical_conflict",
    "sub_category": "iran_warning",
    "affected_tickers": [
      "BA",
      "GLD",
      "SPY"
    ],
    "sector_impact": [
      "defense_military",
      "broad_market"
    ],
    "ticker_impact_weights": {
      "BA": 0.4,
      "GLD": 0.3,
      "SPY": 0.2
    }
  },
  "e1292dbe-8061-42d4-9122-2ce48bb4c988": {
    "event_category": "corporate_action",
    "sub_category": "live_stream_event",
    "affected_tickers": [
      "COIN"
    ],
    "sector_impact": [
      "financials",
      "technology"
    ],
    "ticker_impact_weights": {
      "COIN": 0.2
    }
  },
  "0f2825e3-0dea-4d15-a41b-617262ddb7f5": {
    "event_category": "other",
    "sub_category": "political_media_appearance",
    "affected_tickers": [
      "DJT"
    ],
    "sector_impact": [
      "media",
      "broad_market"
    ],
    "ticker_impact_weights": {
      "DJT": 0.5
    }
  },
  "2e6dbf64-96b9-4bb3-abc3-a83b5a541ffe": {
    "event_category": "regulatory",
    "sub_category": "antitrust_comment",
    "affected_tickers": [
      "GOOG",
      "META",
      "MSFT",
      "AAPL",
      "AMZN",
      "SPY"
    ],
    "sector_impact": [
      "technology",
      "media"
    ],
    "ticker_impact_weights": {
      "GOOG": 1.0,
      "META": 0.3,
      "MSFT": 0.2,
      "AAPL": 0.2,
      "AMZN": 0.2,
      "SPY": 0.1
    }
  },
  "468ffa27-b509-4f72-a55d-0cb54d604533": {
    "event_category": "other",
    "sub_category": "political_statement",
    "affected_tickers": [
      "DJT"
    ],
    "sector_impact": [
      "media",
      "broad_market"
    ],
    "ticker_impact_weights": {
      "DJT": 0.4
    }
  },
  "25b9c302-f515-4576-8d36-1a569c9f991e": {
    "event_category": "other",
    "sub_category": "political_statement",
    "affected_tickers": [
      "DJT"
    ],
    "sector_impact": [
      "media",
      "broad_market"
    ],
    "ticker_impact_weights": {
      "DJT": 0.5
    }
  },
  "55ed4ce7-6a0d-44fb-bac2-c3b73070acd7": {
    "event_category": "corporate_action",
    "sub_category": "nuclear_energy_investment",
    "affected_tickers": [
      "AMZN",
      "SPY"
    ],
    "sector_impact": [
      "technology",
      "energy_commodity"
    ],
    "ticker_impact_weights": {
      "AMZN": 1.0,
      "SPY": 0.2
    }
  },
  "2bdc4a3a-7ad4-4c69-bff9-a1da50cdd3de": {
    "event_category": "corporate_action",
    "sub_category": "nuclear_energy_investment",
    "affected_tickers": [
      "AMZN",
      "SPY"
    ],
    "sector_impact": [
      "technology",
      "energy_commodity"
    ],
    "ticker_impact_weights": {
      "AMZN": 1.0,
      "SPY": 0.2
    }
  },
  "45d4a49c-2c72-4620-ba7f-d567ae0d0bf2": {
    "event_category": "energy_commodity",
    "sub_category": "nuclear_energy_funding",
    "affected_tickers": [
      "AMZN",
      "SPY"
    ],
    "sector_impact": [
      "energy_commodity",
      "technology"
    ],
    "ticker_impact_weights": {
      "AMZN": 0.3,
      "SPY": 0.1
    }
  },
  "a86d45e2-e6cd-4e33-896c-e6db364f5ff0": {
    "event_category": "corporate_action",
    "sub_category": "executive_departure",
    "affected_tickers": [
      "AAPL"
    ],
    "sector_impact": [
      "technology"
    ],
    "ticker_impact_weights": {
      "AAPL": 1.0
    }
  },
  "4b69d6b4-9400-4b0e-b263-03a32a52534d": {
    "event_category": "corporate_action",
    "sub_category": "executive_departure",
    "affected_tickers": [
      "GOOG",
      "MSFT",
      "META"
    ],
    "sector_impact": [
      "technology",
      "communication_services"
    ],
    "ticker_impact_weights": {
      "GOOG": 1.0,
      "MSFT": 0.3,
      "META": 0.3
    }
  },
  "9490f831-ec56-42ec-a612-490d97df71d1": {
    "event_category": "earnings_data",
    "sub_category": "q3_earnings",
    "affected_tickers": [
      "NFLX",
      "META",
      "GOOG",
      "AMZN",
      "SPY",
      "QQQ"
    ],
    "sector_impact": [
      "technology",
      "communication_services",
      "broad_market"
    ],
    "ticker_impact_weights": {
      "NFLX": 1.0,
      "META": 0.5,
      "GOOG": 0.4,
      "AMZN": 0.4,
      "SPY": 0.2,
      "QQQ": 0.3
    }
  },
  "a5797d6b-e5f3-40b2-9a38-afec539c2c40": {
    "event_category": "earnings_data",
    "sub_category": "q3_earnings",
    "affected_tickers": [
      "NFLX",
      "META",
      "GOOG",
      "AMZN",
      "SPY",
      "QQQ"
    ],
    "sector_impact": [
      "technology",
      "communication_services",
      "broad_market"
    ],
    "ticker_impact_weights": {
      "NFLX": 1.0,
      "META": 0.5,
      "GOOG": 0.4,
      "AMZN": 0.4,
      "SPY": 0.2,
      "QQQ": 0.3
    }
  },
  "dca512c8-7112-4a7f-85e7-8c0fa7e0d9e4": {
    "event_category": "regulatory",
    "sub_category": "export_controls",
    "affected_tickers": [
      "TSM",
      "NVDA",
      "AMD",
      "INTC",
      "AVGO",
      "SMCI"
    ],
    "sector_impact": [
      "technology",
      "semiconductors",
      "trade_policy"
    ],
    "ticker_impact_weights": {
      "TSM": 1.0,
      "NVDA": 0.6,
      "AMD": 0.6,
      "INTC": 0.5,
      "AVGO": 0.5,
      "SMCI": 0.4
    }
  },
  "9563116f-9cd6-4757-be4a-fec93e9cd6b3": {
    "event_category": "market_structure",
    "sub_category": "pre_market_movement",
    "affected_tickers": [
      "TSM",
      "NVDA",
      "AMD",
      "INTC",
      "AVGO",
      "SMCI"
    ],
    "sector_impact": [
      "semiconductors",
      "technology",
      "broad_market"
    ],
    "ticker_impact_weights": {
      "TSM": 1.0,
      "NVDA": 0.6,
      "AMD": 0.5,
      "INTC": 0.5,
      "AVGO": 0.5,
      "SMCI": 0.4
    }
  },
  "5af7af98-bc5e-4329-a3d0-30cb88325dde": {
    "event_category": "other",
    "sub_category": "political_personnel",
    "affected_tickers": [
      "JPM"
    ],
    "sector_impact": [
      "financials",
      "broad_market"
    ],
    "ticker_impact_weights": {
      "JPM": 1.0
    }
  },
  "e20b49e6-92c0-49f7-9e7b-1f7fdfc1e7c0": {
    "event_category": "regulatory",
    "sub_category": "enforcement",
    "affected_tickers": [],
    "sector_impact": [
      "financials",
      "broad_market"
    ],
    "ticker_impact_weights": {}
  },
  "6c160989-8c44-4f7f-949e-ea4a52e7c2ca": {
    "event_category": "regulatory",
    "sub_category": "enforcement",
    "affected_tickers": [],
    "sector_impact": [
      "financials",
      "broad_market"
    ],
    "ticker_impact_weights": {}
  },
  "57434e1f-1f31-4991-b269-6826e72d000b": {
    "event_category": "other",
    "sub_category": "health_safety",
    "affected_tickers": [],
    "sector_impact": [
      "consumer_discretionary",
      "consumer_staples"
    ],
    "ticker_impact_weights": {}
  },
  "1745fcb6-6f6d-478e-a325-cdaa682bf4f8": {
    "event_category": "other",
    "sub_category": "health_safety",
    "affected_tickers": [],
    "sector_impact": [
      "consumer_discretionary",
      "consumer_staples"
    ],
    "ticker_impact_weights": {}
  },
  "413b0270-1467-4daa-9fab-cf3c4e8a4709": {
    "event_category": "corporate_action",
    "sub_category": "merger_acquisition",
    "affected_tickers": [],
    "sector_impact": [
      "industrials",
      "airlines"
    ],
    "ticker_impact_weights": {}
  },
  "a83c2488-242d-4747-9df0-c008994d4256": {
    "event_category": "earnings_data",
    "sub_category": "guidance_update",
    "affected_tickers": [],
    "sector_impact": [
      "business_services"
    ],
    "ticker_impact_weights": {}
  },
  "8d87767e-a4f1-432e-9484-e8a31f97efa8": {
    "event_category": "other",
    "sub_category": "health_safety",
    "affected_tickers": [],
    "sector_impact": [
      "consumer_discretionary",
      "consumer_staples"
    ],
    "ticker_impact_weights": {}
  },
  "c4d4bf9d-0508-4f5d-9735-47b138244263": {
    "event_category": "other",
    "sub_category": "sales_volume",
    "affected_tickers": [],
    "sector_impact": [
      "consumer_discretionary"
    ],
    "ticker_impact_weights": {}
  },
  "871cafa2-5c7d-438e-8253-0ecae867e6b1": {
    "event_category": "regulatory",
    "sub_category": "regulatory_inquiry",
    "affected_tickers": [],
    "sector_impact": [
      "financials"
    ],
    "ticker_impact_weights": {}
  },
  "d3fe0a67-0c78-4b43-81e5-9530240014d8": {
    "event_category": "earnings_data",
    "sub_category": "q3_earnings",
    "affected_tickers": [
      "TSLA",
      "SPY",
      "QQQ"
    ],
    "sector_impact": [
      "technology",
      "consumer_discretionary",
      "automotive",
      "broad_market"
    ],
    "ticker_impact_weights": {
      "TSLA": 1.0,
      "SPY": 0.2,
      "QQQ": 0.3
    }
  },
  "552daa5d-3c5e-4dd9-bf62-c3547887db4c": {
    "event_category": "earnings_data",
    "sub_category": "q3_earnings",
    "affected_tickers": [
      "TSLA",
      "SPY",
      "QQQ"
    ],
    "sector_impact": [
      "technology",
      "consumer_discretionary",
      "automotive",
      "broad_market"
    ],
    "ticker_impact_weights": {
      "TSLA": 1.0,
      "SPY": 0.2,
      "QQQ": 0.3
    }
  },
  "079d91e8-a333-4280-bc94-929cec1ea47d": {
    "event_category": "corporate_action",
    "sub_category": "production_update",
    "affected_tickers": [
      "TSLA",
      "SPY",
      "QQQ"
    ],
    "sector_impact": [
      "technology",
      "consumer_discretionary",
      "automotive",
      "broad_market"
    ],
    "ticker_impact_weights": {
      "TSLA": 1.0,
      "SPY": 0.2,
      "QQQ": 0.3
    }
  },
  "69e78972-d98a-4b17-acfd-c75a109a97bf": {
    "event_category": "labor_market",
    "sub_category": "labor_dispute",
    "affected_tickers": [
      "BA"
    ],
    "sector_impact": [
      "industrials",
      "defense",
      "aviation"
    ],
    "ticker_impact_weights": {
      "BA": 1.0
    }
  },
  "aac05fd3-7125-4c5a-a12a-edc4345710f3": {
    "event_category": "labor_market",
    "sub_category": "labor_dispute",
    "affected_tickers": [
      "BA"
    ],
    "sector_impact": [
      "industrials",
      "defense",
      "aviation"
    ],
    "ticker_impact_weights": {
      "BA": 1.0
    }
  },
  "44abc067-b925-4210-9961-c9a6647f63b3": {
    "event_category": "corporate_action",
    "sub_category": "merger_blocked",
    "affected_tickers": [],
    "sector_impact": [
      "consumer_discretionary",
      "luxury_goods"
    ],
    "ticker_impact_weights": {}
  },
  "04b57930-d6bf-4ba8-9f0b-216a3e294dea": {
    "event_category": "corporate_action",
    "sub_category": "earnings_call_cancellation",
    "affected_tickers": [],
    "sector_impact": [
      "consumer_discretionary"
    ],
    "ticker_impact_weights": {}
  },
  "bc7a88ad-3beb-4a3f-974d-6ea0b9a0d48d": {
    "event_category": "geopolitical_conflict",
    "sub_category": "executive_foreign_contact",
    "affected_tickers": [
      "TSLA"
    ],
    "sector_impact": [
      "technology",
      "defense_military",
      "broad_market"
    ],
    "ticker_impact_weights": {
      "TSLA": 0.7
    }
  },
  "d398ee14-03de-4dbf-b5c9-ae860c876aee": {
    "event_category": "market_structure",
    "sub_category": "market_cap_rank",
    "affected_tickers": [
      "NVDA",
      "AAPL",
      "QQQ",
      "SPY",
      "AMD"
    ],
    "sector_impact": [
      "technology",
      "broad_market"
    ],
    "ticker_impact_weights": {
      "NVDA": 0.9,
      "AAPL": 0.8,
      "QQQ": 0.4,
      "SPY": 0.3,
      "AMD": 0.2
    }
  },
  "39e37740-81e9-4e24-8e2c-2f08d03bb21f": {
    "event_category": "geopolitical_conflict",
    "sub_category": "cyber_espionage",
    "affected_tickers": [
      "DJT",
      "SPY"
    ],
    "sector_impact": [
      "media",
      "technology",
      "broad_market"
    ],
    "ticker_impact_weights": {
      "DJT": 0.5,
      "SPY": 0.1
    }
  },
  "3477717d-145e-45b2-a9d3-c2f34ab1a081": {
    "event_category": "corporate_action",
    "sub_category": "data_breach",
    "affected_tickers": [
      "DJT"
    ],
    "sector_impact": [
      "media",
      "technology"
    ],
    "ticker_impact_weights": {
      "DJT": 0.9
    }
  },
  "430334c6-04c4-4444-aab5-d416b1c58f7e": {
    "event_category": "regulatory",
    "sub_category": "lawsuit_filing",
    "affected_tickers": [],
    "sector_impact": [
      "consumer_discretionary",
      "transportation"
    ],
    "ticker_impact_weights": {}
  },
  "7302a14d-b343-42c0-9094-eba8eb1e4532": {
    "event_category": "regulatory",
    "sub_category": "settlement",
    "affected_tickers": [],
    "sector_impact": [
      "consumer_discretionary",
      "transportation"
    ],
    "ticker_impact_weights": {}
  },
  "2c3f3396-58f0-44c7-bc1e-7439d5c10b66": {
    "event_category": "geopolitical_conflict",
    "sub_category": "military_strike",
    "affected_tickers": [
      "GLD",
      "BA",
      "SPY"
    ],
    "sector_impact": [
      "energy_commodity",
      "defense_military",
      "broad_market"
    ],
    "ticker_impact_weights": {
      "GLD": 0.4,
      "BA": 0.3,
      "SPY": 0.2
    }
  },
  "91f2d8ec-dfac-400b-9d13-0c5737f20070": {
    "event_category": "geopolitical_conflict",
    "sub_category": "military_strike_update",
    "affected_tickers": [
      "GLD",
      "BA",
      "SPY"
    ],
    "sector_impact": [
      "energy_commodity",
      "defense_military",
      "broad_market"
    ],
    "ticker_impact_weights": {
      "GLD": 0.3,
      "BA": 0.2,
      "SPY": 0.2
    }
  },
  "25ddaa07-c74e-448b-a7fb-2ec6f7b93abd": {
    "event_category": "corporate_action",
    "sub_category": "product_safety_update",
    "affected_tickers": [],
    "sector_impact": [
      "consumer_staples",
      "restaurants"
    ],
    "ticker_impact_weights": {}
  },
  "ec9f502c-c69c-4fcc-9f97-701c0a6d9859": {
    "event_category": "corporate_action",
    "sub_category": "supply_chain_update",
    "affected_tickers": [],
    "sector_impact": [
      "consumer_staples",
      "restaurants"
    ],
    "ticker_impact_weights": {}
  },
  "55629cf9-088d-4c94-aa97-fb50f53797ab": {
    "event_category": "tech_sector",
    "sub_category": "ai_product_development",
    "affected_tickers": [
      "META",
      "GOOG",
      "QQQ",
      "SPY",
      "NVDA"
    ],
    "sector_impact": [
      "technology",
      "broad_market"
    ],
    "ticker_impact_weights": {
      "META": 1.0,
      "GOOG": 0.6,
      "QQQ": 0.3,
      "SPY": 0.2,
      "NVDA": 0.2
    }
  },
  "1e8964df-9bc6-4f77-8307-0d4c84d3a32c": {
    "event_category": "market_structure",
    "sub_category": "market_reaction",
    "affected_tickers": [
      "GOOG",
      "META",
      "QQQ",
      "SPY"
    ],
    "sector_impact": [
      "technology",
      "broad_market"
    ],
    "ticker_impact_weights": {
      "GOOG": 1.0,
      "META": 0.7,
      "QQQ": 0.4,
      "SPY": 0.3
    }
  },
  "b68522f7-5f0e-428b-8ce3-8df38079f5a8": {
    "event_category": "tech_sector",
    "sub_category": "ai_commentary",
    "affected_tickers": [
      "MSFT",
      "NVDA",
      "QQQ",
      "GOOG",
      "AMZN",
      "META",
      "AAPL",
      "SPY"
    ],
    "sector_impact": [
      "technology",
      "broad_market"
    ],
    "ticker_impact_weights": {
      "MSFT": 0.8,
      "NVDA": 0.6,
      "QQQ": 0.4,
      "GOOG": 0.3,
      "AMZN": 0.3,
      "META": 0.3,
      "AAPL": 0.2,
      "SPY": 0.2
    }
  },
  "422c27ba-c846-465c-a6be-97fe743ee03f": {
    "event_category": "corporate_action",
    "sub_category": "takeover_interest",
    "affected_tickers": [],
    "sector_impact": [
      "technology"
    ],
    "ticker_impact_weights": {}
  },
  "32941e17-a8b1-4998-975b-b92a1f3e3dba": {
    "event_category": "tech_sector",
    "sub_category": "executive_forecast",
    "affected_tickers": [
      "TSLA",
      "NVDA",
      "QQQ",
      "SPY"
    ],
    "sector_impact": [
      "technology",
      "industrial",
      "broad_market"
    ],
    "ticker_impact_weights": {
      "TSLA": 0.9,
      "NVDA": 0.2,
      "QQQ": 0.2,
      "SPY": 0.1
    }
  },
  "b42aa84e-0109-4b4d-bd0e-c8a6ebe017d0": {
    "event_category": "tech_sector",
    "sub_category": "autonomous_vehicles",
    "affected_tickers": [
      "TSLA",
      "QQQ",
      "SPY"
    ],
    "sector_impact": [
      "technology",
      "automotive",
      "broad_market"
    ],
    "ticker_impact_weights": {
      "TSLA": 1.0,
      "QQQ": 0.2,
      "SPY": 0.1
    }
  },
  "4feaa9fa-5cf8-40bc-b73b-f01367502516": {
    "event_category": "corporate_action",
    "sub_category": "merger_update",
    "affected_tickers": [],
    "sector_impact": [
      "transportation",
      "airlines"
    ],
    "ticker_impact_weights": {}
  },
  "f3c5ffdb-acb3-4119-9263-7be8977d06e7": {
    "event_category": "tech_sector",
    "sub_category": "chip_development",
    "affected_tickers": [
      "AVGO",
      "NVDA",
      "AMD",
      "MSFT",
      "TSM",
      "QQQ",
      "SPY"
    ],
    "sector_impact": [
      "technology",
      "semiconductor"
    ],
    "ticker_impact_weights": {
      "AVGO": 1.0,
      "NVDA": 0.8,
      "AMD": 0.5,
      "MSFT": 0.5,
      "TSM": 0.3,
      "QQQ": 0.3,
      "SPY": 0.2
    }
  },
  "b13191db-f066-4c08-bd53-26afbc65bb06": {
    "event_category": "tech_sector",
    "sub_category": "manufacturing_agreement",
    "affected_tickers": [
      "TSM",
      "MSFT",
      "NVDA",
      "AMD",
      "QQQ",
      "SPY"
    ],
    "sector_impact": [
      "technology",
      "semiconductor"
    ],
    "ticker_impact_weights": {
      "TSM": 1.0,
      "MSFT": 0.5,
      "NVDA": 0.3,
      "AMD": 0.3,
      "QQQ": 0.3,
      "SPY": 0.2
    }
  },
  "1e49dacd-e299-4a50-8831-b8d0714644ce": {
    "event_category": "tech_sector",
    "sub_category": "fundraising",
    "affected_tickers": [
      "TSLA",
      "NVDA",
      "QQQ",
      "MSFT",
      "GOOG"
    ],
    "sector_impact": [
      "technology",
      "broad_market"
    ],
    "ticker_impact_weights": {
      "TSLA": 0.7,
      "NVDA": 0.3,
      "QQQ": 0.2,
      "MSFT": 0.2,
      "GOOG": 0.2
    }
  },
  "a1bd1dcd-aa0a-4ebf-b073-f9bc971619dc": {
    "event_category": "corporate_action",
    "sub_category": "executive_guidance",
    "affected_tickers": [
      "INTC",
      "AMD",
      "NVDA",
      "QQQ",
      "SPY"
    ],
    "sector_impact": [
      "technology",
      "semiconductors",
      "broad_market"
    ],
    "ticker_impact_weights": {
      "INTC": 1.0,
      "AMD": 0.6,
      "NVDA": 0.3,
      "QQQ": 0.25,
      "SPY": 0.2
    }
  },
  "72c92630-2833-4c43-831d-9a6db803c850": {
    "event_category": "labor_market",
    "sub_category": "layoff_announcement",
    "affected_tickers": [
      "SPY",
      "QQQ"
    ],
    "sector_impact": [
      "financials",
      "payment_processing",
      "broad_market"
    ],
    "ticker_impact_weights": {
      "SPY": 0.15,
      "QQQ": 0.1
    }
  },
  "12b797b9-34fc-4b75-9af3-f21e7cf8201e": {
    "event_category": "earnings_data",
    "sub_category": "q3_earnings_cloud",
    "affected_tickers": [
      "GOOG",
      "MSFT",
      "AMZN",
      "AVGO",
      "QCOM",
      "QQQ",
      "SPY"
    ],
    "sector_impact": [
      "technology",
      "cloud_computing",
      "broad_market"
    ],
    "ticker_impact_weights": {
      "GOOG": 1.0,
      "MSFT": 0.4,
      "AMZN": 0.35,
      "AVGO": 0.3,
      "QCOM": 0.25,
      "QQQ": 0.35,
      "SPY": 0.25
    }
  },
  "fb683e1f-a694-406b-a0c1-9b17b8115d82": {
    "event_category": "earnings_data",
    "sub_category": "q3_earnings_eps",
    "affected_tickers": [
      "GOOG",
      "MSFT",
      "AMZN",
      "QQQ",
      "SPY"
    ],
    "sector_impact": [
      "technology",
      "broad_market"
    ],
    "ticker_impact_weights": {
      "GOOG": 1.0,
      "MSFT": 0.3,
      "AMZN": 0.3,
      "QQQ": 0.35,
      "SPY": 0.25
    }
  },
  "6f3558d6-bdb5-4545-94b7-8df792052a6b": {
    "event_category": "earnings_data",
    "sub_category": "q3_earnings_revenue",
    "affected_tickers": [
      "GOOG",
      "META",
      "AMZN",
      "QQQ",
      "SPY"
    ],
    "sector_impact": [
      "technology",
      "advertising",
      "broad_market"
    ],
    "ticker_impact_weights": {
      "GOOG": 1.0,
      "META": 0.4,
      "AMZN": 0.3,
      "QQQ": 0.35,
      "SPY": 0.25
    }
  },
  "ba0de43c-20fb-4d44-aaa4-03a458006723": {
    "event_category": "earnings_data",
    "sub_category": "q3_earnings_ad_revenue",
    "affected_tickers": [
      "GOOG",
      "META",
      "SPY",
      "QQQ"
    ],
    "sector_impact": [
      "technology",
      "advertising",
      "broad_market"
    ],
    "ticker_impact_weights": {
      "GOOG": 1.0,
      "META": 0.5,
      "SPY": 0.2,
      "QQQ": 0.3
    }
  },
  "e4ab6efc-41ed-4697-a3a2-f67bd7515b45": {
    "event_category": "market_structure",
    "sub_category": "insider_filing",
    "affected_tickers": [
      "GME",
      "SPY"
    ],
    "sector_impact": [
      "consumer_discretionary",
      "retail"
    ],
    "ticker_impact_weights": {
      "GME": 0.25,
      "SPY": 0.1
    }
  },
  "262af2b0-1497-445b-bf83-4d3bed1539fa": {
    "event_category": "labor_market",
    "sub_category": "corporate_layoffs",
    "affected_tickers": [
      "SPY",
      "QQQ",
      "GOOG",
      "MSFT",
      "AMZN"
    ],
    "sector_impact": [
      "technology",
      "cloud_storage",
      "broad_market"
    ],
    "ticker_impact_weights": {
      "SPY": 0.15,
      "QQQ": 0.2,
      "GOOG": 0.2,
      "MSFT": 0.15,
      "AMZN": 0.15
    }
  },
  "24b0320b-ca39-48ed-835f-6802e2683951": {
    "event_category": "labor_market",
    "sub_category": "crypto_layoffs",
    "affected_tickers": [
      "COIN",
      "MSTR",
      "SPY"
    ],
    "sector_impact": [
      "financials",
      "cryptocurrency",
      "broad_market"
    ],
    "ticker_impact_weights": {
      "COIN": 0.7,
      "MSTR": 0.4,
      "SPY": 0.1
    }
  },
  "30fea809-ee6b-49da-971c-c60347ec16ff": {
    "event_category": "geopolitical_conflict",
    "sub_category": "election_political",
    "affected_tickers": [
      "TSLA",
      "DJT",
      "SPY",
      "QQQ"
    ],
    "sector_impact": [
      "broad_market",
      "technology",
      "financials"
    ],
    "ticker_impact_weights": {
      "TSLA": 0.5,
      "DJT": 0.4,
      "SPY": 0.3,
      "QQQ": 0.3
    }
  },
  "3422a895-5f51-4aa9-ad96-4d4db180e692": {
    "event_category": "market_structure",
    "sub_category": "insider_sale",
    "affected_tickers": [
      "AMZN",
      "SPY"
    ],
    "sector_impact": [
      "technology",
      "e_commerce",
      "broad_market"
    ],
    "ticker_impact_weights": {
      "AMZN": 0.5,
      "SPY": 0.15
    }
  },
  "7a9ed7e8-7447-4b00-a702-a0ed9e73fd46": {
    "event_category": "geopolitical_conflict",
    "sub_category": "election_returns",
    "affected_tickers": [
      "DJT",
      "TSLA",
      "SPY",
      "BA",
      "QQQ"
    ],
    "sector_impact": [
      "broad_market",
      "defense",
      "financials"
    ],
    "ticker_impact_weights": {
      "DJT": 0.5,
      "TSLA": 0.3,
      "SPY": 0.25,
      "BA": 0.25,
      "QQQ": 0.2
    }
  },
  "f7d67fc1-f1ba-4dca-a961-105de387641f": {
    "event_category": "geopolitical_conflict",
    "sub_category": "election_returns",
    "affected_tickers": [
      "DJT",
      "TSLA",
      "SPY",
      "BA",
      "QQQ"
    ],
    "sector_impact": [
      "broad_market",
      "defense",
      "financials"
    ],
    "ticker_impact_weights": {
      "DJT": 0.5,
      "TSLA": 0.3,
      "SPY": 0.25,
      "BA": 0.25,
      "QQQ": 0.2
    }
  },
  "a63395c6-4d65-4201-821e-69c183f30e29": {
    "event_category": "geopolitical_conflict",
    "sub_category": "election_results_senate",
    "affected_tickers": [
      "BA",
      "SPY",
      "QQQ"
    ],
    "sector_impact": [
      "defense",
      "broad_market",
      "financials"
    ],
    "ticker_impact_weights": {
      "BA": 0.6,
      "SPY": 0.3,
      "QQQ": 0.2
    }
  },
  "b6fd4803-b076-45e4-8674-76fc84e9bce0": {
    "event_category": "geopolitical_conflict",
    "sub_category": "election_results_senate",
    "affected_tickers": [
      "BA",
      "SPY",
      "QQQ"
    ],
    "sector_impact": [
      "defense",
      "broad_market",
      "financials"
    ],
    "ticker_impact_weights": {
      "BA": 0.6,
      "SPY": 0.3,
      "QQQ": 0.2
    }
  },
  "566c8216-9194-4628-a0f3-1f6329b13bd1": {
    "event_category": "geopolitical_conflict",
    "sub_category": "election_returns",
    "affected_tickers": [
      "SPY",
      "QQQ"
    ],
    "sector_impact": [
      "broad_market",
      "financials"
    ],
    "ticker_impact_weights": {
      "SPY": 0.2,
      "QQQ": 0.2
    }
  },
  "81d883dd-e8f3-46e8-bf49-ea1062669665": {
    "event_category": "geopolitical_conflict",
    "sub_category": "election_results",
    "affected_tickers": [
      "DJT",
      "TSLA",
      "BA",
      "SPY",
      "QQQ"
    ],
    "sector_impact": [
      "broad_market",
      "defense",
      "financials"
    ],
    "ticker_impact_weights": {
      "DJT": 0.8,
      "TSLA": 0.4,
      "BA": 0.35,
      "SPY": 0.3,
      "QQQ": 0.25
    }
  },
  "e95c9ad4-60b9-43c3-961c-17cb126d8fb8": {
    "event_category": "geopolitical_conflict",
    "sub_category": "election_results",
    "affected_tickers": [
      "DJT",
      "TSLA",
      "BA",
      "JPM",
      "SPY",
      "QQQ",
      "COIN"
    ],
    "sector_impact": [
      "broad_market",
      "defense",
      "financials",
      "energy"
    ],
    "ticker_impact_weights": {
      "DJT": 1.0,
      "TSLA": 0.5,
      "BA": 0.4,
      "JPM": 0.35,
      "SPY": 0.35,
      "QQQ": 0.3,
      "COIN": 0.3
    }
  },
  "650659c3-4669-4f58-9d01-32e599c453d2": {
    "event_category": "corporate_action",
    "sub_category": "strategic_partnership",
    "affected_tickers": [
      "INTC",
      "NVDA",
      "AMD",
      "MSFT",
      "QQQ",
      "SPY"
    ],
    "sector_impact": [
      "technology",
      "automotive",
      "semiconductors"
    ],
    "ticker_impact_weights": {
      "INTC": 0.3,
      "NVDA": 0.25,
      "AMD": 0.25,
      "MSFT": 0.2,
      "QQQ": 0.2,
      "SPY": 0.15
    }
  },
  "18f6446c-1303-46ee-a6f2-d4af1f99da5d": {
    "event_category": "corporate_action",
    "sub_category": "executive_announcement",
    "affected_tickers": [
      "JPM",
      "SPY",
      "QQQ"
    ],
    "sector_impact": [
      "financials",
      "broad_market"
    ],
    "ticker_impact_weights": {
      "JPM": 0.9,
      "SPY": 0.2,
      "QQQ": 0.15
    }
  },
  "e2bfb98f-7df6-4aad-9dc6-fbfb59aeabab": {
    "event_category": "geopolitical_conflict",
    "sub_category": "election_results",
    "affected_tickers": [
      "SPY",
      "QQQ"
    ],
    "sector_impact": [
      "broad_market",
      "financials"
    ],
    "ticker_impact_weights": {
      "SPY": 0.15,
      "QQQ": 0.15
    }
  },
  "82c76075-b81f-48f2-a4b1-c90ed009b990": {
    "event_category": "other",
    "sub_category": "election_transition",
    "affected_tickers": [
      "SPY",
      "QQQ",
      "JPM"
    ],
    "sector_impact": [
      "broad_market",
      "financials"
    ],
    "ticker_impact_weights": {
      "SPY": 0.5,
      "QQQ": 0.4,
      "JPM": 0.3
    }
  },
  "0dbd242d-3d78-4686-abeb-2ad1e840e360": {
    "event_category": "other",
    "sub_category": "election_transition",
    "affected_tickers": [
      "SPY",
      "QQQ"
    ],
    "sector_impact": [
      "broad_market"
    ],
    "ticker_impact_weights": {
      "SPY": 0.5,
      "QQQ": 0.4
    }
  },
  "2cdfdece-97ab-4b72-8152-c0e46ed44a1c": {
    "event_category": "fed_policy",
    "sub_category": "fed_chair_tenure",
    "affected_tickers": [
      "SPY",
      "QQQ",
      "JPM",
      "MSFT",
      "AAPL"
    ],
    "sector_impact": [
      "financials",
      "broad_market"
    ],
    "ticker_impact_weights": {
      "SPY": 0.7,
      "QQQ": 0.6,
      "JPM": 0.5,
      "MSFT": 0.3,
      "AAPL": 0.3
    }
  },
  "6cd33031-449c-4d98-9564-1dc622c08312": {
    "event_category": "geopolitical_conflict",
    "sub_category": "ukraine_russia_conflict",
    "affected_tickers": [
      "BA",
      "SPY",
      "QQQ"
    ],
    "sector_impact": [
      "defense_military",
      "energy_commodity",
      "broad_market"
    ],
    "ticker_impact_weights": {
      "BA": 0.4,
      "SPY": 0.3,
      "QQQ": 0.3
    }
  },
  "66079f60-0bc9-42bf-b9eb-d5cd65f5d20f": {
    "event_category": "fed_policy",
    "sub_category": "fed_chair_tenure",
    "affected_tickers": [
      "SPY",
      "QQQ",
      "JPM",
      "MSFT",
      "AAPL"
    ],
    "sector_impact": [
      "financials",
      "broad_market"
    ],
    "ticker_impact_weights": {
      "SPY": 0.7,
      "QQQ": 0.6,
      "JPM": 0.5,
      "MSFT": 0.3,
      "AAPL": 0.3
    }
  },
  "8bcb2feb-b9b8-4f19-8a38-01faba7b67dd": {
    "event_category": "corporate_action",
    "sub_category": "executive_statement",
    "affected_tickers": [
      "SPY",
      "QQQ"
    ],
    "sector_impact": [
      "technology",
      "media"
    ],
    "ticker_impact_weights": {
      "SPY": 0.2,
      "QQQ": 0.3
    }
  },
  "d645a9f8-58a6-453c-9440-96c2304d3e25": {
    "event_category": "corporate_action",
    "sub_category": "market_cap_milestone",
    "affected_tickers": [
      "TSLA",
      "SPY",
      "QQQ",
      "META",
      "GOOG",
      "AMZN",
      "AAPL",
      "NVDA",
      "MSFT"
    ],
    "sector_impact": [
      "technology",
      "automotive",
      "broad_market"
    ],
    "ticker_impact_weights": {
      "TSLA": 1.0,
      "SPY": 0.5,
      "QQQ": 0.5,
      "META": 0.4,
      "GOOG": 0.4,
      "AMZN": 0.4,
      "AAPL": 0.4,
      "NVDA": 0.4,
      "MSFT": 0.4
    }
  },
  "1c0e56d0-0b7d-4644-a5d9-5e62e2a7d46c": {
    "event_category": "regulatory",
    "sub_category": "legal_proceedings",
    "affected_tickers": [
      "SPY",
      "QQQ"
    ],
    "sector_impact": [
      "broad_market"
    ],
    "ticker_impact_weights": {
      "SPY": 0.3,
      "QQQ": 0.3
    }
  },
  "161c8dfd-9de8-479f-a171-8a3bf54a59f8": {
    "event_category": "geopolitical_conflict",
    "sub_category": "ukraine_russia_conflict",
    "affected_tickers": [
      "BA",
      "SPY",
      "QQQ"
    ],
    "sector_impact": [
      "defense_military",
      "technology",
      "broad_market"
    ],
    "ticker_impact_weights": {
      "BA": 0.4,
      "SPY": 0.3,
      "QQQ": 0.3
    }
  },
  "10cfb808-b35d-439f-9836-277a8ab530e3": {
    "event_category": "trade_policy",
    "sub_category": "export_controls",
    "affected_tickers": [
      "AMD",
      "INTC",
      "AVGO",
      "SMCI",
      "NVDA",
      "TSM",
      "QQQ",
      "SPY"
    ],
    "sector_impact": [
      "technology",
      "semiconductors"
    ],
    "ticker_impact_weights": {
      "AMD": 0.7,
      "INTC": 0.6,
      "AVGO": 0.5,
      "SMCI": 0.5,
      "NVDA": 0.4,
      "TSM": 0.4,
      "QQQ": 0.5,
      "SPY": 0.3
    }
  },
  "387bfffe-6589-4658-89dd-c83c5fba59d7": {
    "event_category": "geopolitical_conflict",
    "sub_category": "ukraine_russia_conflict",
    "affected_tickers": [
      "BA",
      "SPY",
      "QQQ"
    ],
    "sector_impact": [
      "defense_military",
      "energy_commodity",
      "broad_market"
    ],
    "ticker_impact_weights": {
      "BA": 0.7,
      "SPY": 0.3,
      "QQQ": 0.3
    }
  },
  "f6d02572-aa8e-40e8-9d73-357f128f19f4": {
    "event_category": "corporate_action",
    "sub_category": "hiring_expansion",
    "affected_tickers": [
      "ORCL",
      "MSFT",
      "AMZN",
      "GOOG",
      "QQQ",
      "SPY"
    ],
    "sector_impact": [
      "technology"
    ],
    "ticker_impact_weights": {
      "ORCL": 1.0,
      "MSFT": 0.4,
      "AMZN": 0.4,
      "GOOG": 0.4,
      "QQQ": 0.4,
      "SPY": 0.2
    }
  },
  "5dc13a03-d91f-4ee6-b31d-289be8bbe268": {
    "event_category": "geopolitical_conflict",
    "sub_category": "middle_east_conflict",
    "affected_tickers": [
      "SPY",
      "QQQ"
    ],
    "sector_impact": [
      "broad_market",
      "energy_commodity"
    ],
    "ticker_impact_weights": {
      "SPY": 0.3,
      "QQQ": 0.3
    }
  },
  "0f5a7839-649a-4da0-820e-7bd2c4824689": {
    "event_category": "geopolitical_conflict",
    "sub_category": "middle_east_conflict",
    "affected_tickers": [
      "SPY",
      "QQQ"
    ],
    "sector_impact": [
      "broad_market",
      "energy_commodity"
    ],
    "ticker_impact_weights": {
      "SPY": 0.3,
      "QQQ": 0.3
    }
  },
  "841adab5-a313-4afd-b4f9-90500eee5399": {
    "event_category": "corporate_action",
    "sub_category": "executive_departure",
    "affected_tickers": [
      "GOOG",
      "SPY",
      "QQQ"
    ],
    "sector_impact": [
      "technology"
    ],
    "ticker_impact_weights": {
      "GOOG": 0.5,
      "SPY": 0.2,
      "QQQ": 0.3
    }
  },
  "2a52b4a8-e803-4be8-9794-2117ad9a46fc": {
    "event_category": "corporate_action",
    "sub_category": "executive_appointment",
    "affected_tickers": [
      "SPY",
      "QQQ"
    ],
    "sector_impact": [
      "financials"
    ],
    "ticker_impact_weights": {
      "SPY": 0.2,
      "QQQ": 0.2
    }
  },
  "78138f2d-f2b3-40bc-8e5d-3f7c2c598c40": {
    "event_category": "regulatory",
    "sub_category": "tech_regulation",
    "affected_tickers": [
      "SPY",
      "QQQ",
      "MSFT",
      "GOOG"
    ],
    "sector_impact": [
      "technology",
      "media"
    ],
    "ticker_impact_weights": {
      "SPY": 0.3,
      "QQQ": 0.4,
      "MSFT": 0.3,
      "GOOG": 0.3
    }
  },
  "13b855b3-d0a2-42f4-9c7c-397fced24796": {
    "event_category": "tech_sector",
    "sub_category": "product_launch",
    "affected_tickers": [
      "AAPL",
      "AMZN",
      "GOOG",
      "MSFT",
      "QQQ",
      "SPY"
    ],
    "sector_impact": [
      "technology",
      "consumer_electronics"
    ],
    "ticker_impact_weights": {
      "AAPL": 1.0,
      "AMZN": 0.4,
      "GOOG": 0.4,
      "MSFT": 0.4,
      "QQQ": 0.5,
      "SPY": 0.3
    }
  },
  "a845368e-2ff5-43b3-8bbc-46673fed543f": {
    "event_category": "corporate_action",
    "sub_category": "insider_sale",
    "affected_tickers": [
      "AMZN",
      "SPY",
      "QQQ"
    ],
    "sector_impact": [
      "technology",
      "broad_market"
    ],
    "ticker_impact_weights": {
      "AMZN": 0.8,
      "SPY": 0.2,
      "QQQ": 0.3
    }
  },
  "9ae99d02-31c8-42cd-8410-dbfe59ab32ae": {
    "event_category": "corporate_action",
    "sub_category": "bankruptcy_filing",
    "affected_tickers": [
      "SPY",
      "QQQ"
    ],
    "sector_impact": [
      "airlines",
      "broad_market"
    ],
    "ticker_impact_weights": {
      "SPY": 0.3,
      "QQQ": 0.2
    }
  },
  "a294b50e-992d-40db-b7b3-0f54cb810695": {
    "event_category": "corporate_action",
    "sub_category": "stock_decline",
    "affected_tickers": [
      "SPY",
      "QQQ"
    ],
    "sector_impact": [
      "airlines",
      "broad_market"
    ],
    "ticker_impact_weights": {
      "SPY": 0.2,
      "QQQ": 0.2
    }
  },
  "be5abc83-5f59-4168-acaf-d42d59f1f29a": {
    "event_category": "corporate_action",
    "sub_category": "filing_delay",
    "affected_tickers": [],
    "sector_impact": [
      "industrials"
    ],
    "ticker_impact_weights": {}
  },
  "6868c9ff-a390-4290-8afa-8f0b468cc10f": {
    "event_category": "tech_sector",
    "sub_category": "ai_policy",
    "affected_tickers": [
      "MSFT",
      "NVDA",
      "GOOG",
      "AMZN",
      "META",
      "QQQ",
      "SPY"
    ],
    "sector_impact": [
      "technology"
    ],
    "ticker_impact_weights": {
      "MSFT": 0.6,
      "NVDA": 0.5,
      "GOOG": 0.4,
      "AMZN": 0.3,
      "META": 0.3,
      "QQQ": 0.3,
      "SPY": 0.1
    }
  },
  "2d7a0fb6-b8b9-423e-884c-8dc92a0a4f43": {
    "event_category": "trade_policy",
    "sub_category": "ai_competition",
    "affected_tickers": [
      "MSFT",
      "NVDA",
      "GOOG",
      "AMZN",
      "META",
      "QQQ",
      "SPY"
    ],
    "sector_impact": [
      "technology",
      "broad_market"
    ],
    "ticker_impact_weights": {
      "MSFT": 0.6,
      "NVDA": 0.5,
      "GOOG": 0.4,
      "AMZN": 0.3,
      "META": 0.3,
      "QQQ": 0.3,
      "SPY": 0.1
    }
  },
  "e6cf72c7-6fe7-4bce-aaa1-d43abdae31d7": {
    "event_category": "corporate_action",
    "sub_category": "layoffs",
    "affected_tickers": [
      "AMD",
      "NVDA",
      "INTC",
      "SMCI",
      "QQQ"
    ],
    "sector_impact": [
      "technology"
    ],
    "ticker_impact_weights": {
      "AMD": 1.0,
      "NVDA": 0.4,
      "INTC": 0.3,
      "SMCI": 0.2,
      "QQQ": 0.2
    }
  },
  "06677b66-f705-4d80-8e6d-fde77b0c475b": {
    "event_category": "tech_sector",
    "sub_category": "product_launch",
    "affected_tickers": [
      "MSFT",
      "NVDA",
      "GOOG",
      "AMZN",
      "META",
      "QQQ",
      "SPY"
    ],
    "sector_impact": [
      "technology"
    ],
    "ticker_impact_weights": {
      "MSFT": 0.7,
      "NVDA": 0.5,
      "GOOG": 0.4,
      "AMZN": 0.3,
      "META": 0.3,
      "QQQ": 0.3,
      "SPY": 0.2
    }
  },
  "716ff563-c85a-4de0-994d-eecac24f4b6e": {
    "event_category": "defense_military",
    "sub_category": "appointment",
    "affected_tickers": [
      "BA",
      "SPY",
      "QQQ"
    ],
    "sector_impact": [
      "defense_military",
      "broad_market"
    ],
    "ticker_impact_weights": {
      "BA": 0.3,
      "SPY": 0.1,
      "QQQ": 0.1
    }
  },
  "bfc092da-d019-4be0-9b05-ff4b38ec033e": {
    "event_category": "geopolitical_conflict",
    "sub_category": "ceasefire_negotiations",
    "affected_tickers": [
      "GLD",
      "SPY",
      "BA",
      "QQQ"
    ],
    "sector_impact": [
      "broad_market",
      "energy_commodity"
    ],
    "ticker_impact_weights": {
      "GLD": 0.3,
      "SPY": 0.2,
      "BA": 0.2,
      "QQQ": 0.1
    }
  },
  "55d8892f-67af-4b17-8893-6d1b73f6f0e6": {
    "event_category": "corporate_action",
    "sub_category": "acquisition",
    "affected_tickers": [],
    "sector_impact": [
      "communication_services"
    ],
    "ticker_impact_weights": {}
  },
  "a31de514-3d82-414f-89df-4f8396c2f06a": {
    "event_category": "fiscal_policy",
    "sub_category": "ev_credit_removal",
    "affected_tickers": [
      "TSLA",
      "QQQ",
      "SPY"
    ],
    "sector_impact": [
      "consumer_discretionary"
    ],
    "ticker_impact_weights": {
      "TSLA": 1.0,
      "QQQ": 0.2,
      "SPY": 0.1
    }
  },
  "03f184f9-07b2-4252-b400-2376747578a2": {
    "event_category": "fiscal_policy",
    "sub_category": "ev_subsidy_stance",
    "affected_tickers": [
      "TSLA",
      "QQQ",
      "SPY"
    ],
    "sector_impact": [
      "consumer_discretionary"
    ],
    "ticker_impact_weights": {
      "TSLA": 1.0,
      "QQQ": 0.2,
      "SPY": 0.1
    }
  },
  "868b7454-27c5-4e1a-b011-69f655bd894a": {
    "event_category": "regulatory",
    "sub_category": "antitrust_investigation",
    "affected_tickers": [
      "MSFT",
      "AMZN",
      "GOOG",
      "QQQ",
      "NVDA",
      "SPY"
    ],
    "sector_impact": [
      "technology"
    ],
    "ticker_impact_weights": {
      "MSFT": 1.0,
      "AMZN": 0.4,
      "GOOG": 0.3,
      "QQQ": 0.3,
      "NVDA": 0.2,
      "SPY": 0.2
    }
  },
  "492edb7b-4587-436a-921f-8e008d107de6": {
    "event_category": "corporate_action",
    "sub_category": "executive_announcement",
    "affected_tickers": [
      "JPM",
      "SPY"
    ],
    "sector_impact": [
      "financials"
    ],
    "ticker_impact_weights": {
      "JPM": 0.7,
      "SPY": 0.1
    }
  },
  "438facd8-f1c0-4e91-9818-3d9b80866cdf": {
    "event_category": "corporate_action",
    "sub_category": "insider_sale",
    "affected_tickers": [
      "AMZN",
      "QQQ",
      "SPY"
    ],
    "sector_impact": [
      "consumer_discretionary",
      "broad_market"
    ],
    "ticker_impact_weights": {
      "AMZN": 1.0,
      "QQQ": 0.4,
      "SPY": 0.3
    }
  },
  "c74365ff-b4a1-4c58-82bc-d7bee1d1183e": {
    "event_category": "geopolitical_conflict",
    "sub_category": "diplomatic_meeting",
    "affected_tickers": [
      "TSLA",
      "SPY",
      "QQQ"
    ],
    "sector_impact": [
      "broad_market"
    ],
    "ticker_impact_weights": {
      "TSLA": 0.5,
      "SPY": 0.1,
      "QQQ": 0.1
    }
  },
  "98a0ebd7-90e1-4fd2-aeb4-e238440504ac": {
    "event_category": "corporate_action",
    "sub_category": "delisting_compliance",
    "affected_tickers": [
      "SMCI",
      "NVDA",
      "AMD",
      "QQQ"
    ],
    "sector_impact": [
      "technology"
    ],
    "ticker_impact_weights": {
      "SMCI": 1.0,
      "NVDA": 0.3,
      "AMD": 0.2,
      "QQQ": 0.2
    }
  },
  "9ece7e8a-25be-4a95-b9b4-e7b8e02d5eb6": {
    "event_category": "corporate_action",
    "sub_category": "acquisition_talks",
    "affected_tickers": [
      "DJT",
      "COIN",
      "MSTR",
      "IBIT",
      "SPY"
    ],
    "sector_impact": [
      "communication_services",
      "financials"
    ],
    "ticker_impact_weights": {
      "DJT": 1.0,
      "COIN": 0.5,
      "MSTR": 0.3,
      "IBIT": 0.3,
      "SPY": 0.1
    }
  },
  "951273f6-bafe-4860-a977-f62141236785": {
    "event_category": "corporate_action",
    "sub_category": "meeting",
    "affected_tickers": [
      "COIN",
      "DJT",
      "MSTR",
      "IBIT",
      "SPY"
    ],
    "sector_impact": [
      "financials",
      "technology"
    ],
    "ticker_impact_weights": {
      "COIN": 1.0,
      "DJT": 0.3,
      "MSTR": 0.3,
      "IBIT": 0.3,
      "SPY": 0.1
    }
  },
  "72c84ab9-c7bc-4d04-b4f5-654e72d58238": {
    "event_category": "corporate_action",
    "sub_category": "meeting",
    "affected_tickers": [
      "COIN",
      "DJT",
      "MSTR",
      "IBIT",
      "SPY"
    ],
    "sector_impact": [
      "financials",
      "technology"
    ],
    "ticker_impact_weights": {
      "COIN": 1.0,
      "DJT": 0.3,
      "MSTR": 0.3,
      "IBIT": 0.3,
      "SPY": 0.1
    }
  },
  "91c45170-9d9c-4904-ad37-8217b80c06ef": {
    "event_category": "defense_military",
    "sub_category": "deployment",
    "affected_tickers": [
      "BA",
      "SPY",
      "QQQ"
    ],
    "sector_impact": [
      "defense_military",
      "broad_market"
    ],
    "ticker_impact_weights": {
      "BA": 0.2,
      "SPY": 0.1,
      "QQQ": 0.1
    }
  },
  "ee0b1138-6964-40e1-a6b4-98ce099f7b62": {
    "event_category": "corporate_action",
    "sub_category": "debt_offering",
    "affected_tickers": [
      "MSTR",
      "COIN",
      "IBIT",
      "SPY"
    ],
    "sector_impact": [
      "technology",
      "financials"
    ],
    "ticker_impact_weights": {
      "MSTR": 1.0,
      "COIN": 0.3,
      "IBIT": 0.3,
      "SPY": 0.1
    }
  },
  "2c33be96-49fa-4163-a7cc-6f68b2b83ff3": {
    "event_category": "corporate_action",
    "sub_category": "executive_resignation",
    "affected_tickers": [
      "AMD",
      "NVDA",
      "INTC",
      "SMCI",
      "QQQ"
    ],
    "sector_impact": [
      "technology"
    ],
    "ticker_impact_weights": {
      "AMD": 1.0,
      "NVDA": 0.2,
      "INTC": 0.2,
      "SMCI": 0.2,
      "QQQ": 0.2
    }
  },
  "f1b238e8-8d00-45a3-9ffd-9acabf9fd19c": {
    "event_category": "tech_sector",
    "sub_category": "ai_summit",
    "affected_tickers": [
      "NVDA",
      "GOOG",
      "MSFT",
      "META"
    ],
    "sector_impact": [
      "technology",
      "broad_market",
      "communication_services"
    ],
    "ticker_impact_weights": {
      "NVDA": 0.5,
      "GOOG": 0.3,
      "MSFT": 0.3,
      "META": 0.3
    }
  },
  "68da25bb-1f16-4527-aaae-054f9df6d34c": {
    "event_category": "corporate_action",
    "sub_category": "auditor_appointment",
    "affected_tickers": [
      "SMCI"
    ],
    "sector_impact": [
      "technology"
    ],
    "ticker_impact_weights": {
      "SMCI": 1.0
    }
  },
  "c8bc7ed6-c17b-445c-a0af-42ebb4c150db": {
    "event_category": "regulatory",
    "sub_category": "listing_compliance",
    "affected_tickers": [
      "SMCI"
    ],
    "sector_impact": [
      "technology"
    ],
    "ticker_impact_weights": {
      "SMCI": 1.0
    }
  },
  "1c51163d-1563-4a8b-9022-16836adf8590": {
    "event_category": "defense_military",
    "sub_category": "space_launch",
    "affected_tickers": [
      "BA"
    ],
    "sector_impact": [
      "defense_military",
      "technology"
    ],
    "ticker_impact_weights": {
      "BA": 0.2
    }
  },
  "0407c822-2163-42eb-b410-6dcc763c48c9": {
    "event_category": "corporate_action",
    "sub_category": "financial_filing",
    "affected_tickers": [
      "SMCI"
    ],
    "sector_impact": [
      "technology"
    ],
    "ticker_impact_weights": {
      "SMCI": 1.0
    }
  },
  "8bedea85-56b8-4af2-9665-ad06c1ad07a7": {
    "event_category": "regulatory",
    "sub_category": "antitrust_enforcement",
    "affected_tickers": [
      "GOOG"
    ],
    "sector_impact": [
      "technology",
      "communication_services"
    ],
    "ticker_impact_weights": {
      "GOOG": 1.0
    }
  },
  "6c1af770-71c5-4eb7-897e-c12465594442": {
    "event_category": "tech_sector",
    "sub_category": "ai_partnerships",
    "affected_tickers": [
      "AMZN",
      "MSFT",
      "GOOG"
    ],
    "sector_impact": [
      "technology",
      "consumer_discretionary"
    ],
    "ticker_impact_weights": {
      "AMZN": 0.8,
      "MSFT": 0.3,
      "GOOG": 0.3
    }
  },
  "044059b7-ed8d-41e2-91fd-8d229fc082c1": {
    "event_category": "market_structure",
    "sub_category": "after_hours_trading",
    "affected_tickers": [
      "SMCI"
    ],
    "sector_impact": [
      "technology"
    ],
    "ticker_impact_weights": {
      "SMCI": 1.0
    }
  },
  "0b8da6a5-a1e6-438b-8387-46a59e5bd6c8": {
    "event_category": "tech_sector",
    "sub_category": "payment_services",
    "affected_tickers": [
      "GOOG"
    ],
    "sector_impact": [
      "technology",
      "financials"
    ],
    "ticker_impact_weights": {
      "GOOG": 0.8
    }
  },
  "0eec457a-0b98-4c06-8886-42d220df4e04": {
    "event_category": "geopolitical_conflict",
    "sub_category": "political_legal",
    "affected_tickers": [
      "DJT"
    ],
    "sector_impact": [
      "broad_market"
    ],
    "ticker_impact_weights": {
      "DJT": 0.5
    }
  },
  "5fbc960d-c7f1-4c54-b1dc-aca666504335": {
    "event_category": "fiscal_policy",
    "sub_category": "trade_policy_appointment",
    "affected_tickers": [],
    "sector_impact": [
      "broad_market",
      "trade_sensitive"
    ],
    "ticker_impact_weights": {}
  },
  "a1b696ff-8255-4a0b-9a8b-42a17f7f9d35": {
    "event_category": "tech_sector",
    "sub_category": "ai_chip_investment",
    "affected_tickers": [
      "NVDA",
      "AMD",
      "INTC",
      "MSFT"
    ],
    "sector_impact": [
      "technology"
    ],
    "ticker_impact_weights": {
      "NVDA": 0.7,
      "AMD": 0.4,
      "INTC": 0.4,
      "MSFT": 0.3
    }
  },
  "f6488b61-0525-489f-b2dd-56d0e0d4f122": {
    "event_category": "tech_sector",
    "sub_category": "ai_chip_investment",
    "affected_tickers": [
      "NVDA",
      "AMD",
      "MSFT"
    ],
    "sector_impact": [
      "technology"
    ],
    "ticker_impact_weights": {
      "NVDA": 0.5,
      "AMD": 0.3,
      "MSFT": 0.3
    }
  },
  "fb074e07-cde1-46f0-920f-57e525629dfb": {
    "event_category": "fiscal_policy",
    "sub_category": "treasury_secretary_appointment",
    "affected_tickers": [
      "JPM"
    ],
    "sector_impact": [
      "broad_market",
      "financials"
    ],
    "ticker_impact_weights": {
      "JPM": 0.3
    }
  },
  "b1330aca-d5f0-450f-b08e-57b1953f8ce6": {
    "event_category": "tech_sector",
    "sub_category": "ai_partnership",
    "affected_tickers": [],
    "sector_impact": [
      "technology"
    ],
    "ticker_impact_weights": {}
  },
  "b34d299d-25d9-499e-889c-4e4c6b183c04": {
    "event_category": "regulatory",
    "sub_category": "listing_compliance",
    "affected_tickers": [
      "SMCI"
    ],
    "sector_impact": [
      "technology"
    ],
    "ticker_impact_weights": {
      "SMCI": 1.0
    }
  },
  "dab1f54c-6a00-4d6c-a6bc-c8658de3b4ea": {
    "event_category": "corporate_action",
    "sub_category": "compliance_statement",
    "affected_tickers": [
      "SMCI"
    ],
    "sector_impact": [
      "technology"
    ],
    "ticker_impact_weights": {
      "SMCI": 1.0
    }
  },
  "296e4ca5-b723-4073-a38a-49e31e3f1540": {
    "event_category": "corporate_action",
    "sub_category": "stock_split",
    "affected_tickers": [],
    "sector_impact": [
      "technology"
    ],
    "ticker_impact_weights": {}
  },
  "a733529e-33f5-4bd2-89e3-485be6432dd9": {
    "event_category": "geopolitical_conflict",
    "sub_category": "political_appointment",
    "affected_tickers": [],
    "sector_impact": [
      "broad_market"
    ],
    "ticker_impact_weights": {}
  },
  "b1fbc74a-d36d-401f-8c60-dc5f873980ae": {
    "event_category": "regulatory",
    "sub_category": "antitrust_investment",
    "affected_tickers": [
      "GOOG",
      "META"
    ],
    "sector_impact": [
      "technology"
    ],
    "ticker_impact_weights": {
      "GOOG": 0.8,
      "META": 0.2
    }
  },
  "4b19af2a-8c07-428c-bdf7-f1c4916fe799": {
    "event_category": "tech_sector",
    "sub_category": "browser_development",
    "affected_tickers": [
      "GOOG",
      "MSFT",
      "META"
    ],
    "sector_impact": [
      "technology",
      "communication_services"
    ],
    "ticker_impact_weights": {
      "GOOG": 0.7,
      "MSFT": 0.4,
      "META": 0.2
    }
  },
  "401e9c1d-c845-4e77-8493-8f845c54e889": {
    "event_category": "regulatory",
    "sub_category": "attorney_general_appointment",
    "affected_tickers": [
      "COIN",
      "JPM",
      "SPY"
    ],
    "sector_impact": [
      "legal_regulatory",
      "broad_market"
    ],
    "ticker_impact_weights": {
      "COIN": 0.3,
      "JPM": 0.2,
      "SPY": 0.2
    }
  },
  "d03b407f-51d5-480e-b493-1706062bbd9b": {
    "event_category": "fed_policy",
    "sub_category": "fed_chair_consideration",
    "affected_tickers": [
      "SPY",
      "QQQ",
      "JPM",
      "GLD"
    ],
    "sector_impact": [
      "financials",
      "broad_market"
    ],
    "ticker_impact_weights": {
      "SPY": 0.8,
      "QQQ": 0.7,
      "JPM": 0.6,
      "GLD": 0.4
    }
  },
  "ead0f89d-eed5-44b0-89b6-73f2abba621c": {
    "event_category": "tech_sector",
    "sub_category": "ai_investment",
    "affected_tickers": [
      "AMZN",
      "NVDA",
      "GOOG",
      "MSFT"
    ],
    "sector_impact": [
      "technology",
      "cloud_computing",
      "AI"
    ],
    "ticker_impact_weights": {
      "AMZN": 1.0,
      "NVDA": 0.7,
      "GOOG": 0.5,
      "MSFT": 0.4
    }
  },
  "afa537bc-42d7-4e5e-a0f7-93a96db2b759": {
    "event_category": "corporate_action",
    "sub_category": "executive_departure",
    "affected_tickers": [],
    "sector_impact": [
      "retail"
    ],
    "ticker_impact_weights": {}
  },
  "8fe96998-3560-4758-afbb-87509378704a": {
    "event_category": "regulatory",
    "sub_category": "chips_act_funding",
    "affected_tickers": [
      "INTC",
      "TSM",
      "AMD",
      "NVDA",
      "AMZN"
    ],
    "sector_impact": [
      "semiconductors",
      "technology"
    ],
    "ticker_impact_weights": {
      "INTC": 1.0,
      "TSM": 0.5,
      "AMD": 0.5,
      "NVDA": 0.4,
      "AMZN": 0.3
    }
  },
  "87465924-cd6d-42d5-967d-104ab5dabf4b": {
    "event_category": "regulatory",
    "sub_category": "ev_tax_credit_exclusion",
    "affected_tickers": [
      "TSLA"
    ],
    "sector_impact": [
      "automotive",
      "energy"
    ],
    "ticker_impact_weights": {
      "TSLA": 1.0
    }
  },
  "9b973358-bd99-45ee-8020-e6dde05eccd3": {
    "event_category": "regulatory",
    "sub_category": "doj_case_dismissal",
    "affected_tickers": [
      "DJT",
      "SPY"
    ],
    "sector_impact": [
      "legal_regulatory"
    ],
    "ticker_impact_weights": {
      "DJT": 0.3,
      "SPY": 0.2
    }
  },
  "a901dd26-b807-4019-9cea-e041310ea7eb": {
    "event_category": "regulatory",
    "sub_category": "chips_act_update",
    "affected_tickers": [
      "INTC",
      "TSM",
      "AMD",
      "NVDA"
    ],
    "sector_impact": [
      "semiconductors",
      "technology"
    ],
    "ticker_impact_weights": {
      "INTC": 0.9,
      "TSM": 0.4,
      "AMD": 0.4,
      "NVDA": 0.3
    }
  },
  "a678087b-623f-4e65-819b-72962cf1ac85": {
    "event_category": "corporate_action",
    "sub_category": "failed_takeover",
    "affected_tickers": [
      "INTC",
      "AMD",
      "NVDA",
      "TSM"
    ],
    "sector_impact": [
      "semiconductors"
    ],
    "ticker_impact_weights": {
      "INTC": 0.9,
      "AMD": 0.5,
      "NVDA": 0.4,
      "TSM": 0.4
    }
  },
  "009a40d9-fd71-449f-979b-a417ef938bba": {
    "event_category": "fiscal_policy",
    "sub_category": "federal_funding_cuts",
    "affected_tickers": [],
    "sector_impact": [
      "government",
      "municipalities"
    ],
    "ticker_impact_weights": {}
  },
  "7c92f9cd-0137-4510-a535-b99b2df9204f": {
    "event_category": "regulatory",
    "sub_category": "drug_scheduling",
    "affected_tickers": [
      "HIMS"
    ],
    "sector_impact": [
      "pharmaceuticals",
      "cannabis"
    ],
    "ticker_impact_weights": {
      "HIMS": 0.3
    }
  },
  "2685fc76-9e7f-43f0-8010-4836152dde14": {
    "event_category": "regulatory",
    "sub_category": "fda_rejection",
    "affected_tickers": [],
    "sector_impact": [
      "pharmaceuticals"
    ],
    "ticker_impact_weights": {}
  },
  "85854363-0205-4d6a-acc9-fd3c76e96097": {
    "event_category": "trade_policy",
    "sub_category": "border_closure",
    "affected_tickers": [
      "TSLA",
      "SPY",
      "AMZN",
      "QQQ"
    ],
    "sector_impact": [
      "trade",
      "immigration"
    ],
    "ticker_impact_weights": {
      "TSLA": 0.4,
      "SPY": 0.3,
      "AMZN": 0.3,
      "QQQ": 0.2
    }
  },
  "df660274-1528-48d9-96b2-9ff9bcfd61db": {
    "event_category": "regulatory",
    "sub_category": "presidential_pardon",
    "affected_tickers": [],
    "sector_impact": [
      "legal_political"
    ],
    "ticker_impact_weights": {}
  },
  "553cb5f5-d114-4c97-a720-0dc6ceb04e48": {
    "event_category": "corporate_action",
    "sub_category": "ceo_departure",
    "affected_tickers": [
      "INTC",
      "AMD",
      "NVDA",
      "QQQ",
      "TSM"
    ],
    "sector_impact": [
      "semiconductors",
      "technology"
    ],
    "ticker_impact_weights": {
      "INTC": 1.0,
      "AMD": 0.6,
      "NVDA": 0.5,
      "QQQ": 0.4,
      "TSM": 0.4
    }
  },
  "722a852a-99dc-4961-8bf4-8e2f5f57e089": {
    "event_category": "corporate_action",
    "sub_category": "investigation_clearance",
    "affected_tickers": [
      "SMCI",
      "NVDA",
      "MSFT"
    ],
    "sector_impact": [
      "technology",
      "servers"
    ],
    "ticker_impact_weights": {
      "SMCI": 1.0,
      "NVDA": 0.3,
      "MSFT": 0.2
    }
  },
  "34a67718-4688-4cb3-bcc3-f76f9a26c673": {
    "event_category": "corporate_action",
    "sub_category": "executive_appointment",
    "affected_tickers": [
      "SMCI",
      "NVDA"
    ],
    "sector_impact": [
      "technology",
      "servers"
    ],
    "ticker_impact_weights": {
      "SMCI": 1.0,
      "NVDA": 0.3
    }
  },
  "eaab1f0e-372a-49e0-b0fe-29e4d49b4f82": {
    "event_category": "geopolitical_conflict",
    "sub_category": "political_crisis",
    "affected_tickers": [
      "SPY",
      "QQQ",
      "TSM"
    ],
    "sector_impact": [
      "broad_market",
      "Asia_risk"
    ],
    "ticker_impact_weights": {
      "SPY": 0.7,
      "QQQ": 0.6,
      "TSM": 0.5
    }
  },
  "e6a17683-2306-4d24-ac93-a3b30de595e9": {
    "event_category": "geopolitical_conflict",
    "sub_category": "political_crisis_resolution",
    "affected_tickers": [
      "SPY",
      "QQQ",
      "TSM"
    ],
    "sector_impact": [
      "broad_market",
      "Asia"
    ],
    "ticker_impact_weights": {
      "SPY": 0.4,
      "QQQ": 0.4,
      "TSM": 0.3
    }
  },
  "3cecd116-01c9-44d2-bf4a-0af1fc2dfb36": {
    "event_category": "geopolitical_conflict",
    "sub_category": "political_crisis_resolution",
    "affected_tickers": [
      "SPY",
      "QQQ",
      "TSM"
    ],
    "sector_impact": [
      "broad_market",
      "Asia"
    ],
    "ticker_impact_weights": {
      "SPY": 0.3,
      "QQQ": 0.3,
      "TSM": 0.2
    }
  },
  "c4db6a6e-20b9-4818-8b7c-aaeaaa0ecb06": {
    "event_category": "tech_sector",
    "sub_category": "ai_infrastructure",
    "affected_tickers": [
      "AMZN",
      "NVDA",
      "AMD",
      "MSFT",
      "GOOG"
    ],
    "sector_impact": [
      "technology",
      "AI",
      "chips"
    ],
    "ticker_impact_weights": {
      "AMZN": 1.0,
      "NVDA": 0.6,
      "AMD": 0.4,
      "MSFT": 0.4,
      "GOOG": 0.4
    }
  },
  "6728e5c2-7871-45ad-8b38-5c2a2512682f": {
    "event_category": "tech_sector",
    "sub_category": "ai_chip_competition",
    "affected_tickers": [
      "NVDA",
      "AMD",
      "AVGO",
      "MSFT"
    ],
    "sector_impact": [
      "semiconductors",
      "technology",
      "cloud_computing"
    ],
    "ticker_impact_weights": {
      "NVDA": 0.8,
      "AMD": 0.5,
      "AVGO": 0.3,
      "MSFT": 0.2
    }
  },
  "b42b58fa-ce62-4e89-938d-f9b7639bdcda": {
    "event_category": "geopolitical_conflict",
    "sub_category": "martial_law_korea",
    "affected_tickers": [
      "SPY",
      "QQQ"
    ],
    "sector_impact": [
      "broad_market",
      "emerging_markets"
    ],
    "ticker_impact_weights": {
      "SPY": 0.3,
      "QQQ": 0.3
    }
  },
  "ebb463d4-503f-4802-85cf-99d04038948f": {
    "event_category": "regulatory",
    "sub_category": "antitrust_investigation",
    "affected_tickers": [
      "MSFT",
      "AAPL",
      "GOOG",
      "META"
    ],
    "sector_impact": [
      "technology",
      "software",
      "cloud_computing"
    ],
    "ticker_impact_weights": {
      "MSFT": 0.9,
      "AAPL": 0.2,
      "GOOG": 0.2,
      "META": 0.2
    }
  },
  "c3fcd7ca-6298-4018-a892-3ff8552de239": {
    "event_category": "geopolitical_conflict",
    "sub_category": "martial_law_resolution",
    "affected_tickers": [
      "SPY",
      "QQQ"
    ],
    "sector_impact": [
      "broad_market",
      "emerging_markets"
    ],
    "ticker_impact_weights": {
      "SPY": 0.2,
      "QQQ": 0.2
    }
  },
  "fdbabfc0-c4d5-49a7-963e-ee1305c14f41": {
    "event_category": "corporate_action",
    "sub_category": "executive_appointment",
    "affected_tickers": [],
    "sector_impact": [
      "technology",
      "cryptocurrency"
    ],
    "ticker_impact_weights": {}
  },
  "bbe47b63-ac83-48fa-a751-6ebc1c0bfdec": {
    "event_category": "market_structure",
    "sub_category": "market_operations",
    "affected_tickers": [
      "SPY",
      "QQQ"
    ],
    "sector_impact": [
      "broad_market"
    ],
    "ticker_impact_weights": {
      "SPY": 0.1,
      "QQQ": 0.1
    }
  },
  "57671561-316d-4369-a329-e925a4752d01": {
    "event_category": "corporate_action",
    "sub_category": "ceo_death",
    "affected_tickers": [
      "UNH"
    ],
    "sector_impact": [
      "healthcare",
      "insurance"
    ],
    "ticker_impact_weights": {
      "UNH": 1.0
    }
  },
  "1cf84612-78ca-427e-af5a-0098b62c7f4c": {
    "event_category": "regulatory",
    "sub_category": "regulatory_appointment",
    "affected_tickers": [
      "SPY",
      "QQQ",
      "JPM"
    ],
    "sector_impact": [
      "financials",
      "broad_market"
    ],
    "ticker_impact_weights": {
      "SPY": 0.4,
      "QQQ": 0.3,
      "JPM": 0.3
    }
  },
  "8e8187bc-69d0-4a6c-839c-5d79f84cb82a": {
    "event_category": "regulatory",
    "sub_category": "forced_divestiture_law",
    "affected_tickers": [
      "META",
      "GOOG"
    ],
    "sector_impact": [
      "technology",
      "social_media"
    ],
    "ticker_impact_weights": {
      "META": 0.6,
      "GOOG": 0.5
    }
  },
  "bba61459-bff2-4fb1-8ee8-4c62e58aed84": {
    "event_category": "regulatory",
    "sub_category": "sportsbook_investigation",
    "affected_tickers": [],
    "sector_impact": [
      "gaming",
      "consumer_discretionary"
    ],
    "ticker_impact_weights": {}
  },
  "7d00f4ca-01df-41e1-90d9-eebebaf864cf": {
    "event_category": "market_structure",
    "sub_category": "index_rebalance",
    "affected_tickers": [],
    "sector_impact": [
      "broad_market",
      "financials"
    ],
    "ticker_impact_weights": {}
  },
  "a7c2ded7-e270-448b-906a-b3db96dffc5d": {
    "event_category": "corporate_action",
    "sub_category": "investigation_update",
    "affected_tickers": [
      "UNH"
    ],
    "sector_impact": [
      "healthcare",
      "insurance"
    ],
    "ticker_impact_weights": {
      "UNH": 0.3
    }
  },
  "dc6854c3-9f59-4f9b-b29e-303f80195a51": {
    "event_category": "earnings_data",
    "sub_category": "pricing_guidance",
    "affected_tickers": [],
    "sector_impact": [
      "media",
      "streaming"
    ],
    "ticker_impact_weights": {}
  },
  "082884ec-ce1f-495c-850b-04935aac031a": {
    "event_category": "corporate_action",
    "sub_category": "leveraged_buyout",
    "affected_tickers": [],
    "sector_impact": [
      "retail",
      "healthcare_retail"
    ],
    "ticker_impact_weights": {}
  },
  "a1f62058-bc03-474f-8625-220aeaa62a0b": {
    "event_category": "trade_policy",
    "sub_category": "foreign_investment_block",
    "affected_tickers": [],
    "sector_impact": [
      "materials",
      "industrial"
    ],
    "ticker_impact_weights": {}
  },
  "fb76e5a9-70b4-47b7-b414-7a567483eb62": {
    "event_category": "fed_policy",
    "sub_category": "rate_cut_expectations",
    "affected_tickers": [
      "SPY",
      "QQQ",
      "JPM"
    ],
    "sector_impact": [
      "financials",
      "broad_market",
      "real_estate"
    ],
    "ticker_impact_weights": {
      "SPY": 0.8,
      "QQQ": 0.7,
      "JPM": 0.5
    }
  },
  "bc483237-8236-4b42-b446-a755b263a7d9": {
    "event_category": "tech_sector",
    "sub_category": "chip_development",
    "affected_tickers": [
      "AAPL",
      "AVGO",
      "NVDA",
      "AMD"
    ],
    "sector_impact": [
      "technology",
      "semiconductors"
    ],
    "ticker_impact_weights": {
      "AAPL": 0.9,
      "AVGO": 0.6,
      "NVDA": 0.5,
      "AMD": 0.3
    }
  },
  "697a91a4-dc17-41bf-8bb2-70ac3681a878": {
    "event_category": "corporate_action",
    "sub_category": "executive_milestone",
    "affected_tickers": [
      "TSLA",
      "MSTR"
    ],
    "sector_impact": [
      "technology",
      "automotive",
      "space"
    ],
    "ticker_impact_weights": {
      "TSLA": 0.7,
      "MSTR": 0.3
    }
  },
  "c44d93bd-23c5-44b2-a4a0-e37fb8752590": {
    "event_category": "geopolitical_conflict",
    "sub_category": "diplomatic_invitation",
    "affected_tickers": [
      "TSM",
      "SPY",
      "QQQ"
    ],
    "sector_impact": [
      "broad_market",
      "technology",
      "semiconductors"
    ],
    "ticker_impact_weights": {
      "TSM": 0.4,
      "SPY": 0.2,
      "QQQ": 0.2
    }
  },
  "b81b7ae2-14e5-4801-89b9-0c94e3434dba": {
    "event_category": "tech_sector",
    "sub_category": "supplier_transition",
    "affected_tickers": [
      "AVGO",
      "AAPL",
      "QCOM",
      "NVDA"
    ],
    "sector_impact": [
      "semiconductors",
      "technology"
    ],
    "ticker_impact_weights": {
      "AVGO": 0.7,
      "AAPL": 0.6,
      "QCOM": 0.4,
      "NVDA": 0.3
    }
  },
  "a4650845-7b24-4755-8b5e-2a6d2d5b9ae6": {
    "event_category": "corporate_action",
    "sub_category": "capital_raising",
    "affected_tickers": [],
    "sector_impact": [
      "technology",
      "bitcoin_mining"
    ],
    "ticker_impact_weights": {}
  },
  "7a2dc32a-6364-4377-8fb5-c6d8210b613a": {
    "event_category": "corporate_action",
    "sub_category": "capital_raise",
    "affected_tickers": [
      "SMCI"
    ],
    "sector_impact": [
      "technology",
      "financials"
    ],
    "ticker_impact_weights": {
      "SMCI": 1.0
    }
  },
  "7f1d85d5-4a94-4426-941d-574e236bdd3e": {
    "event_category": "corporate_action",
    "sub_category": "board_change",
    "affected_tickers": [],
    "sector_impact": [
      "technology",
      "communication_services"
    ],
    "ticker_impact_weights": {}
  },
  "a77dd699-b784-43e1-8bed-35a212c782f0": {
    "event_category": "market_structure",
    "sub_category": "index_addition",
    "affected_tickers": [
      "PLTR",
      "MSTR",
      "QQQ"
    ],
    "sector_impact": [
      "technology"
    ],
    "ticker_impact_weights": {
      "PLTR": 1.0,
      "MSTR": 1.0,
      "QQQ": 0.3
    }
  },
  "44145d66-89e2-412a-8d0b-b56ca5b3c55e": {
    "event_category": "market_structure",
    "sub_category": "index_removal",
    "affected_tickers": [
      "SMCI",
      "QQQ"
    ],
    "sector_impact": [
      "technology",
      "healthcare"
    ],
    "ticker_impact_weights": {
      "SMCI": 1.0,
      "QQQ": 0.3
    }
  },
  "057afc8f-f432-44dc-a595-80b79ac56766": {
    "event_category": "regulatory",
    "sub_category": "tiktok_policy_statement",
    "affected_tickers": [
      "DJT",
      "META",
      "GOOG"
    ],
    "sector_impact": [
      "communication_services",
      "technology"
    ],
    "ticker_impact_weights": {
      "DJT": 0.3,
      "META": 0.3,
      "GOOG": 0.3
    }
  },
  "8dafa3c3-808e-4be1-b7b0-49fa3bd25841": {
    "event_category": "regulatory",
    "sub_category": "antitrust_personnel_change",
    "affected_tickers": [
      "SPY",
      "QQQ",
      "AAPL",
      "AMZN",
      "META",
      "GOOG",
      "MSFT"
    ],
    "sector_impact": [
      "technology",
      "broad_market"
    ],
    "ticker_impact_weights": {
      "SPY": 0.3,
      "QQQ": 0.3,
      "AAPL": 0.4,
      "AMZN": 0.4,
      "META": 0.4,
      "GOOG": 0.4,
      "MSFT": 0.4
    }
  },
  "c739617b-8ce5-4b9e-ad9e-a1de65dad4b5": {
    "event_category": "trade_policy",
    "sub_category": "export_control_probe",
    "affected_tickers": [
      "NVDA",
      "SMCI",
      "AMD",
      "AVGO",
      "TSM",
      "INTC",
      "SPY",
      "QQQ"
    ],
    "sector_impact": [
      "technology",
      "semiconductors",
      "broad_market"
    ],
    "ticker_impact_weights": {
      "NVDA": 1.0,
      "SMCI": 1.0,
      "AMD": 0.6,
      "AVGO": 0.5,
      "TSM": 0.5,
      "INTC": 0.3,
      "SPY": 0.2,
      "QQQ": 0.2
    }
  },
  "91c7573f-3c62-4fe4-80b3-b60324fe34d8": {
    "event_category": "corporate_action",
    "sub_category": "spinoff",
    "affected_tickers": [],
    "sector_impact": [
      "industrials",
      "transportation"
    ],
    "ticker_impact_weights": {}
  },
  "d2675774-5652-4a2c-966e-41f5904713e5": {
    "event_category": "corporate_action",
    "sub_category": "strategic_investment",
    "affected_tickers": [
      "COIN",
      "MSTR",
      "IBIT",
      "DJT"
    ],
    "sector_impact": [
      "technology",
      "cryptocurrency",
      "media"
    ],
    "ticker_impact_weights": {
      "COIN": 0.4,
      "MSTR": 0.3,
      "IBIT": 0.3,
      "DJT": 0.2
    }
  }
}